{"Title":"Dreamgirls","Year":"2006","Rated":"PG-13","Released":"25 Dec 2006","Runtime":"130 min","Genre":"Drama, Musical","Director":"Bill Condon","Writer":"Tom Eyen, Bill Condon","Actors":"Beyoncé, Jamie Foxx, Eddie Murphy","Plot":"Detroit, the early 1960s. Curtis Taylor, Jr., a car salesman, breaks into the music business with big dreams. He signs a trio of young women, the Dreamettes, gets them a job backing an R&amp;B performer, James \"Thunder\" Early, establishes his own record label and starts wheeling and dealing. When Early flames out, Curtis makes the Dreamettes into headliners as the Dreams, but not before demoting their hefty big-voiced lead singer, Effie White, and putting the softer-voiced looker, Deena Jones, in front. Soon after, he fires Effie, sends her into a life of proud poverty, and takes Deena and the Dreams to the top. How long can Curtis stay there, and will Effie ever get her due?","Language":"English","Country":"United States","Awards":"Won 2 Oscars. 67 wins & 93 nominations total","Poster":"https://m.media-amazon.com/images/M/MV5BMTY1MzIwNDQyNl5BMl5BanBnXkFtZTcwNDEwNzYyMw@@._V1_SX300.jpg","Ratings":[{"Source":"Internet Movie Database","Value":"6.6/10"},{"Source":"Rotten Tomatoes","Value":"79%"},{"Source":"Metacritic","Value":"76/100"}],"Metascore":"76","imdbRating":"6.6","imdbVotes":"78,973","imdbID":"tt0443489","Type":"movie","DVD":"N/A","BoxOffice":"$103,365,956","Production":"N/A","Website":"N/A","Response":"True"}