{"Title":"Luis Enrique presenta: No tenéis ni **** idea","Year":"2024–","Rated":"N/A","Released":"01 Oct 2024","Runtime":"N/A","Genre":"Sport","Director":"N/A","Writer":"N/A","Actors":"N/A","Plot":"N/A","Language":"Spanish","Country":"Spain","Awards":"N/A","Poster":"https://m.media-amazon.com/images/M/MV5BMzBhN2QxOTItYjVkZS00Mjg0LTlmMzItOTVmMGU3YzY1MmQ4XkEyXkFqcGc@._V1_SX300.jpg","Ratings":[],"Metascore":"N/A","imdbRating":"N/A","imdbVotes":"10","imdbID":"tt33829541","Type":"series","totalSeasons":"N/A","Response":"True"}