{"Title":"The Gardener","Year":"2025","Rated":"TV-MA","Released":"11 Apr 2025","Runtime":"N/A","Genre":"Drama, Mystery, Thriller","Director":"N/A","Writer":"N/A","Actors":"Álvaro Rico, Cecilia Suárez, Catalina Sopelana","Plot":"Elmer and his controlling mother La China Jurado have a contract killing business. Emotionless after an accident, Elmer falls for Violeta, a teacher he's hired to kill. He must learn to love while his mother tries to eliminate Vio...","Language":"Spanish","Country":"Spain","Awards":"N/A","Poster":"https://m.media-amazon.com/images/M/MV5BYWMxNTNlOGUtNjVlNi00MTRkLWIyMTQtMmViODkxM2M5MjA0XkEyXkFqcGc@._V1_SX300.jpg","Ratings":[{"Source":"Internet Movie Database","Value":"6.3/10"}],"Metascore":"N/A","imdbRating":"6.3","imdbVotes":"4,603","imdbID":"tt30494784","Type":"series","totalSeasons":"1","Response":"True"}