{"Title":"Ryman's Club","Year":"2022","Rated":"N/A","Released":"30 Jan 2022","Runtime":"N/A","Genre":"Animation, Sport","Director":"N/A","Writer":"N/A","Actors":"Brianna Roberts, Jack Reeder, James Larabee","Plot":"Mikoto Shiratori is a childhood prodigy at badminton that lost in high school; after joining the sales department of the Sunlight Beverage company, he starts playing badminton again.","Language":"Japanese","Country":"Japan","Awards":"1 win & 2 nominations total","Poster":"https://m.media-amazon.com/images/M/MV5BODRhNjliNmYtNDYzMS00Yzc2LThlYmUtMTZhMWVmNWRjNWVmXkEyXkFqcGc@._V1_SX300.jpg","Ratings":[{"Source":"Internet Movie Database","Value":"7.0/10"}],"Metascore":"N/A","imdbRating":"7.0","imdbVotes":"258","imdbID":"tt15744206","Type":"series","totalSeasons":"1","Response":"True"}