{"Title":"Irreversible","Year":"2002","Rated":"Not Rated","Released":"22 May 2002","Runtime":"97 min","Genre":"Crime, Drama, Mystery","Director":"Gaspar Noé","Writer":"Gaspar Noé","Actors":"Monica Bellucci, Vincent Cassel, Albert Dupontel","Plot":"A young woman, Alex, is raped by a stranger in a tunnel. Her boyfriend Marcus and ex-boyfriend Pierre decide to do justice themselves. In 2002, Gaspar Noé created controversy (and controversy) by presenting his film at the Cannes Film Festival. 17 years later, he returns with a brand new version of his cult film. Initially operated in an anechronological form (the film starts at the end and ends at its beginning), with Irreversible \"Full Inversion\" (2019), the filmmaker offers us a completely different reading, offering it to us in a chronological order.","Language":"French, Spanish, Italian, English","Country":"France","Awards":"3 wins & 13 nominations total","Poster":"https://m.media-amazon.com/images/M/MV5BZTE2MWM1NTgtMGVjMy00ZGU2LWE4YTUtNTRlNWRhZWE2NmM0XkEyXkFqcGc@._V1_SX300.jpg","Ratings":[{"Source":"Internet Movie Database","Value":"7.3/10"},{"Source":"Rotten Tomatoes","Value":"59%"},{"Source":"Metacritic","Value":"51/100"}],"Metascore":"51","imdbRating":"7.3","imdbVotes":"161,409","imdbID":"tt0290673","Type":"movie","DVD":"N/A","BoxOffice":"$803,491","Production":"N/A","Website":"N/A","Response":"True"}