{"Title":"Avatar: Fire and Ash","Year":"2025","Rated":"PG-13","Released":"19 Dec 2025","Runtime":"197 min","Genre":"Animation, Action, Adventure","Director":"James Cameron","Writer":"James Cameron, Rick Jaffa, Amanda Silver","Actors":"Sam Worthington, Zoe Saldaña, Sigourney Weaver","Plot":"Sequel of Avatar 2 (2022). The plot is unknown.","Language":"English","Country":"United States, Canada","Awards":"Nominated for 2 Oscars. 28 wins & 64 nominations total","Poster":"https://m.media-amazon.com/images/M/MV5BZDYxY2I1OGMtN2Y4MS00ZmU1LTgyNDAtODA0MzAyYjI0N2Y2XkEyXkFqcGc@._V1_SX300.jpg","Ratings":[{"Source":"Internet Movie Database","Value":"7.4/10"},{"Source":"Rotten Tomatoes","Value":"66%"},{"Source":"Metacritic","Value":"61/100"}],"Metascore":"61","imdbRating":"7.4","imdbVotes":"134,356","imdbID":"tt1757678","Type":"movie","DVD":"N/A","BoxOffice":"$401,636,328","Production":"N/A","Website":"N/A","Response":"True"}