{"Title":"Lightyear","Year":"2022","Rated":"PG","Released":"17 Jun 2022","Runtime":"105 min","Genre":"Animation, Action, Adventure","Director":"Angus MacLane","Writer":"Angus MacLane, Matthew Aldrich, Jason Headley","Actors":"Chris Evans, Keke Palmer, Peter Sohn","Plot":"While spending years attempting to return home, marooned Space Ranger Buzz Lightyear encounters an army of ruthless robots commanded by Zurg who are attempting to steal the fuel source of his ship.","Language":"English","Country":"United States, Canada","Awards":"2 wins & 22 nominations total","Poster":"https://m.media-amazon.com/images/M/MV5BZGI3ZjUyM2ItNmFjYy00NGE3LTg2OTYtMTI2MDk0MjIxNDA1XkEyXkFqcGc@._V1_SX300.jpg","Ratings":[{"Source":"Internet Movie Database","Value":"6.1/10"},{"Source":"Rotten Tomatoes","Value":"74%"},{"Source":"Metacritic","Value":"60/100"}],"Metascore":"60","imdbRating":"6.1","imdbVotes":"134,805","imdbID":"tt10298810","Type":"movie","DVD":"N/A","BoxOffice":"$118,307,188","Production":"N/A","Website":"N/A","Response":"True"}