{"Title":"Nobody 2","Year":"2025","Rated":"R","Released":"15 Aug 2025","Runtime":"89 min","Genre":"Action, Comedy, Crime","Director":"Timo Tjahjanto","Writer":"Derek Kolstad, Aaron Rabin","Actors":"Bob Odenkirk, Connie Nielsen, Christopher Lloyd","Plot":"Suburban dad Hutch Mansell, a former lethal assassin, is pulled back into his violent past after thwarting a home invasion, setting off a chain of events.","Language":"English","Country":"United States, Canada","Awards":"3 nominations total","Poster":"https://m.media-amazon.com/images/M/MV5BOWViZjhjYjQtZDI1MC00MWMyLTlhZTktNmIzY2Y0ZWVkMWFhXkEyXkFqcGc@._V1_SX300.jpg","Ratings":[{"Source":"Internet Movie Database","Value":"6.3/10"},{"Source":"Rotten Tomatoes","Value":"76%"},{"Source":"Metacritic","Value":"59/100"}],"Metascore":"59","imdbRating":"6.3","imdbVotes":"76,417","imdbID":"tt28996126","Type":"movie","DVD":"N/A","BoxOffice":"$21,604,985","Production":"N/A","Website":"N/A","Response":"True"}