{"Title":"25th Hour","Year":"2002","Rated":"R","Released":"10 Jan 2003","Runtime":"135 min","Genre":"Drama","Director":"Spike Lee","Writer":"David Benioff","Actors":"Edward Norton, Barry Pepper, Philip Seymour Hoffman","Plot":"The 25th Hour depicts the last day of freedom for a young man before he begins serving a seven-year jail term for drug dealing. Prowling through the city until dawn with his two close male friends and his girlfriend, he is forced to re-examine his life and how he got himself into his predicament, which leads to a shocking, disturbing finale.","Language":"English","Country":"United States","Awards":"4 wins & 17 nominations total","Poster":"https://m.media-amazon.com/images/M/MV5BMjg0OWI0ZjktZTM0My00NmI3LTkzNDEtYzJiODE1ODM0MDk3XkEyXkFqcGc@._V1_SX300.jpg","Ratings":[{"Source":"Internet Movie Database","Value":"7.6/10"},{"Source":"Rotten Tomatoes","Value":"80%"},{"Source":"Metacritic","Value":"69/100"}],"Metascore":"69","imdbRating":"7.6","imdbVotes":"187,630","imdbID":"tt0307901","Type":"movie","DVD":"N/A","BoxOffice":"$13,084,595","Production":"N/A","Website":"N/A","Response":"True"}