{"Title":"The Expanse","Year":"2015–2022","Rated":"TV-14","Released":"23 Nov 2015","Runtime":"60 min","Genre":"Drama, Mystery, Sci-Fi","Director":"N/A","Writer":"Daniel Abraham, Mark Fergus, Ty Franck","Actors":"Steven Strait, Dominique Tipper, Wes Chatham","Plot":"Two hundred years from now, the solar system's been colonized, and police detective, Josephus Miller's given the assignment of finding a missing woman. Meanwhile, an officer of an ice freighter sees what appears to be an unprovoked attack upon the ship, by a craft from Mars. As news of the attack spreads, the incident's repercussions threaten to destabilize an already tenuous relations between Earth, Mars and the asteroid belt.","Language":"English","Country":"United States","Awards":"7 wins & 32 nominations total","Poster":"https://m.media-amazon.com/images/M/MV5BYzUyYmI3MjctY2Q2MC00NmFjLTgwZGUtNWQzZWNlYmVjNzE2XkEyXkFqcGc@._V1_SX300.jpg","Ratings":[{"Source":"Internet Movie Database","Value":"8.5/10"}],"Metascore":"N/A","imdbRating":"8.5","imdbVotes":"189,397","imdbID":"tt3230854","Type":"series","totalSeasons":"6","Response":"True"}