{"Title":"La La Land","Year":"2016","Rated":"PG-13","Released":"25 Dec 2016","Runtime":"128 min","Genre":"Comedy, Drama, Music","Director":"Damien Chazelle","Writer":"Damien Chazelle","Actors":"Ryan Gosling, Emma Stone, Rosemarie DeWitt","Plot":"Aspiring actress serves lattes to movie stars in between auditions and jazz musician Sebastian scrapes by playing cocktail-party gigs in dingy bars. But as success mounts, they are faced with decisions that fray the fragile fabric of their love affair, and the dreams they worked so hard to maintain in each other threaten to rip them apart.","Language":"English, Cantonese","Country":"United States, Hong Kong","Awards":"Won 6 Oscars. 242 wins & 307 nominations total","Poster":"https://m.media-amazon.com/images/M/MV5BMzUzNDM2NzM2MV5BMl5BanBnXkFtZTgwNTM3NTg4OTE@._V1_SX300.jpg","Ratings":[{"Source":"Internet Movie Database","Value":"8.0/10"},{"Source":"Rotten Tomatoes","Value":"91%"},{"Source":"Metacritic","Value":"94/100"}],"Metascore":"94","imdbRating":"8.0","imdbVotes":"751,618","imdbID":"tt3783958","Type":"movie","DVD":"N/A","BoxOffice":"$151,101,803","Production":"N/A","Website":"N/A","Response":"True"}