{"Title":"Harry Potter and the Half-Blood Prince","Year":"2009","Rated":"PG","Released":"15 Jul 2009","Runtime":"153 min","Genre":"Action, Adventure, Family","Director":"David Yates","Writer":"Steve Kloves, J.K. Rowling","Actors":"Daniel Radcliffe, Emma Watson, Rupert Grint","Plot":"During Harry Potter's sixth year at Hogwarts, he finds a book that once belonged to the mysterious Half-Blood Prince that earns him the respect of his new Potions professor Horace Slughorn. In addition, Dumbledore must prepare Harry for the ultimate final confrontation by finding out the secret behind Voldemort's power. Meanwhile, a hidden enemy waits in the shadows to carry out a mission given to him by the Dark Lord.","Language":"English, Latin","Country":"United Kingdom, United States","Awards":"Nominated for 1 Oscar. 9 wins & 39 nominations total","Poster":"https://m.media-amazon.com/images/M/MV5BNzU3NDg4NTAyNV5BMl5BanBnXkFtZTcwOTg2ODg1Mg@@._V1_SX300.jpg","Ratings":[{"Source":"Internet Movie Database","Value":"7.6/10"},{"Source":"Rotten Tomatoes","Value":"83%"},{"Source":"Metacritic","Value":"78/100"}],"Metascore":"78","imdbRating":"7.6","imdbVotes":"653,701","imdbID":"tt0417741","Type":"movie","DVD":"N/A","BoxOffice":"$302,334,374","Production":"N/A","Website":"N/A","Response":"True"}