{"Title":"Warfare","Year":"2025","Rated":"R","Released":"11 Apr 2025","Runtime":"95 min","Genre":"Action, Drama, War","Director":"Alex Garland, Ray Mendoza","Writer":"Ray Mendoza, Alex Garland","Actors":"D'Pharaoh Woon-A-Tai, Will Poulter, Cosmo Jarvis","Plot":"A platoon of Navy SEALs embark on a dangerous mission in Ramadi, Iraq, with the chaos and brotherhood of war retold through their memories of the event.","Language":"English","Country":"United States, United Kingdom","Awards":"Nominated for 1 BAFTA Award7 wins & 26 nominations total","Poster":"https://m.media-amazon.com/images/M/MV5BYzEyYjE1NmEtOTFmNy00ZmQxLThlYzctOGRjNmQ0N2VjMmNmXkEyXkFqcGc@._V1_SX300.jpg","Ratings":[{"Source":"Internet Movie Database","Value":"7.1/10"},{"Source":"Rotten Tomatoes","Value":"92%"},{"Source":"Metacritic","Value":"78/100"}],"Metascore":"78","imdbRating":"7.1","imdbVotes":"105,413","imdbID":"tt31434639","Type":"movie","DVD":"N/A","BoxOffice":"$26,000,309","Production":"N/A","Website":"N/A","Response":"True"}