{"Title":"The Cleaning Lady","Year":"2022–2025","Rated":"TV-MA","Released":"03 Jan 2022","Runtime":"N/A","Genre":"Crime, Drama, Thriller","Director":"Michael Offer","Writer":"Miranda Kwok","Actors":"Elodie Yung, Martha Millan, Sean Lew","Plot":"A whip-smart Cambodian doctor comes to the U.S. for a medical treatment to save her son, but when the system fails and pushes her into hiding, she uses her cunning and intelligence to fight back, breaking the law for all the right reasons.","Language":"English","Country":"United States","Awards":"5 wins & 12 nominations total","Poster":"https://m.media-amazon.com/images/M/MV5BZWFlYzk1YWYtNmEzYy00MWEyLWFiMTktZDg0MmE3ODMzNWZlXkEyXkFqcGc@._V1_SX300.jpg","Ratings":[{"Source":"Internet Movie Database","Value":"7.0/10"}],"Metascore":"N/A","imdbRating":"7.0","imdbVotes":"12,697","imdbID":"tt11188682","Type":"series","totalSeasons":"4","Response":"True"}