{"Title":"The Manager","Year":"2018–","Rated":"N/A","Released":"10 Mar 2018","Runtime":"N/A","Genre":"Comedy, Family, Reality-TV","Director":"N/A","Writer":"N/A","Actors":"Jun Hyun-moo, Yang Se-hyung, Yoo Byung-jae","Plot":"Celebrities and their managers reveal their work schedule and daily routine. Celebrity guests watch and comment on the recorded lives of these superstars.","Language":"Korean","Country":"South Korea","Awards":"N/A","Poster":"https://m.media-amazon.com/images/M/MV5BNTE4ZjQ5YWEtZDNhOC00MmU2LWE0MGMtNjA4Y2MzMDE3ODIxXkEyXkFqcGc@._V1_SX300.jpg","Ratings":[],"Metascore":"N/A","imdbRating":"N/A","imdbVotes":"11","imdbID":"tt15340934","Type":"series","totalSeasons":"1","Response":"True"}