{"id":1154598,"cast":[{"adult":false,"gender":1,"id":75037,"known_for_department":"Acting","name":"Laura Bailey","original_name":"Laura Bailey","popularity":1.6237,"profile_path":"\/44wqOhHZiW3hyBhiky56DcnqOxW.jpg","cast_id":1,"character":"Black Widow \/ Little Girl \/ Sister (voice)","credit_id":"653777ad946318010014102a","order":0},{"adult":false,"gender":2,"id":82816,"known_for_department":"Acting","name":"Trevor Devall","original_name":"Trevor Devall","popularity":0.8162,"profile_path":"\/iCFqgVzkhLkMOw9DKmUmfQ3OyCZ.jpg","cast_id":2,"character":"Red Guardian \/ Hydra Goon 1 (voice)","credit_id":"653777b34083b3013713b214","order":1},{"adult":false,"gender":2,"id":9640,"known_for_department":"Acting","name":"Haley Joel Osment","original_name":"Haley Joel Osment","popularity":3.0547,"profile_path":"\/2rnMTQB9Q3vLtmRyyUaenVwSgfY.jpg","cast_id":15,"character":"The Collector (voice)","credit_id":"653bcbcecc9683012cf31bcd","order":2},{"adult":false,"gender":2,"id":571562,"known_for_department":"Acting","name":"Steve Blum","original_name":"Steve Blum","popularity":1.4339,"profile_path":"\/cpO0muunoigq1WHegeOEI1AIQAo.jpg","cast_id":3,"character":"Wolverine \/ Wendigo 3 \/ Hydra Goon 5 (voice)","credit_id":"653777b81f748b013eb51dcb","order":3},{"adult":false,"gender":2,"id":76621,"known_for_department":"Acting","name":"Will Friedle","original_name":"Will Friedle","popularity":0.7179,"profile_path":"\/Ao3fp9f4loVQ1Vvk6ph8HU5p0Lu.jpg","cast_id":4,"character":"Hydra Goon 3 (voice)","credit_id":"653777bdc50ad200eb2dd8ce","order":4},{"adult":false,"gender":2,"id":1252366,"known_for_department":"Acting","name":"James C. Mathis III","original_name":"James C. Mathis III","popularity":0.3539,"profile_path":"\/m2K3qkTJYtpSOWbEKRLBsAM8W9H.jpg","cast_id":5,"character":"Black Panther (voice)","credit_id":"653777c441aac4011a7cb1ae","order":5},{"adult":false,"gender":2,"id":89966,"known_for_department":"Acting","name":"Liam O'Brien","original_name":"Liam O'Brien","popularity":1.4102,"profile_path":"\/ko7Bba6fQEaAbVFAp1kQHTzuYCp.jpg","cast_id":6,"character":"Red Skull \/ Hydra Goon 2 (voice)","credit_id":"653777cb7fcab3014e36668f","order":6},{"adult":false,"gender":1,"id":228121,"known_for_department":"Acting","name":"Laura Post","original_name":"Laura Post","popularity":0.5604,"profile_path":"\/q95vgGRfaweU7ro1O4VA7KR11RY.jpg","cast_id":7,"character":"Red She-Hulk \/ Milk Woman \/ Computer Voice (voice)","credit_id":"653777d04083b300c3c9a0e0","order":7},{"adult":false,"gender":2,"id":35111,"known_for_department":"Acting","name":"Bumper Robinson","original_name":"Bumper Robinson","popularity":1.0994,"profile_path":"\/9KU72zZXIfsGAPgHmhlJmTYvor9.jpg","cast_id":8,"character":"Captain America - Sam Wilson \/ Hydra Goon 4 (voice)","credit_id":"653777d841aac4011a7cb1ba","order":8},{"adult":false,"gender":2,"id":75038,"known_for_department":"Acting","name":"Roger Craig Smith","original_name":"Roger Craig Smith","popularity":1.1493,"profile_path":"\/6oE356GbRHAf91Llw7LDpvsAf5L.jpg","cast_id":9,"character":"Captain America - Steve Rogers \/ Red Ghost \/ Brother (voice)","credit_id":"653777ddae3668010b9bc72c","order":9},{"adult":false,"gender":2,"id":60279,"known_for_department":"Acting","name":"Fred Tatasciore","original_name":"Fred Tatasciore","popularity":2.3082,"profile_path":"\/7pxLvE4l5mQkGzHLIEwYrc9AMFe.jpg","cast_id":10,"character":"Hulk \/ Wendigo 1 \/ Santa Claus (voice)","credit_id":"653777e141aac400fdde2c69","order":10},{"adult":false,"gender":2,"id":1221888,"known_for_department":"Acting","name":"Travis Willingham","original_name":"Travis Willingham","popularity":0.9739,"profile_path":"\/clvP30k6cUMf4hukRQqZD3k9z4S.jpg","cast_id":11,"character":"Thor \/ Wendigo 2 (voice)","credit_id":"653777e57fcab3014e36669c","order":11},{"adult":false,"gender":2,"id":971877,"known_for_department":"Acting","name":"Mick Wingert","original_name":"Mick Wingert","popularity":1.171,"profile_path":"\/2Apga68BihekhCSPHNk5pXqC5Gq.jpg","cast_id":12,"character":"Iron Man \/ Omega Red \/ Hot Dog Vendor (voice)","credit_id":"653777e8c50ad2012df4b0b6","order":12}],"crew":[{"adult":false,"gender":2,"id":2327912,"known_for_department":"Art","name":"Kevin Chai","original_name":"Kevin Chai","popularity":0.1492,"profile_path":null,"credit_id":"653ce893e894a600ff168a59","department":"Art","job":"Art Direction"},{"adult":false,"gender":0,"id":1693212,"known_for_department":"Production","name":"Harrison Wilcox","original_name":"Harrison Wilcox","popularity":0.4836,"profile_path":null,"credit_id":"653ce84a109cd000c947be79","department":"Writing","job":"Story"},{"adult":false,"gender":2,"id":1237909,"known_for_department":"Writing","name":"Eugene Son","original_name":"Eugene Son","popularity":0.4023,"profile_path":null,"credit_id":"653ce833109cd000ad6234bd","department":"Writing","job":"Writer"},{"adult":false,"gender":2,"id":1237909,"known_for_department":"Writing","name":"Eugene Son","original_name":"Eugene Son","popularity":0.4023,"profile_path":null,"credit_id":"653ce83fbc2cb3014d4a7622","department":"Writing","job":"Story"},{"adult":false,"gender":0,"id":2087770,"known_for_department":"Sound","name":"Steffan Andrews","original_name":"Steffan Andrews","popularity":0.2611,"profile_path":null,"credit_id":"653ce868cc9683014eb8f03c","department":"Sound","job":"Original Music Composer"},{"adult":false,"gender":0,"id":966797,"known_for_department":"Production","name":"Collette Sunderman","original_name":"Collette Sunderman","popularity":0.1949,"profile_path":null,"credit_id":"653ce884cc9683012cf399a9","department":"Production","job":"Casting Director"},{"adult":false,"gender":2,"id":2741073,"known_for_department":"Directing","name":"Ken Cunningham","original_name":"Ken Cunningham","popularity":0.4756,"profile_path":"\/8e2qCGzpDXvAsLdPpzrUyDamyqD.jpg","credit_id":"653ba2d6519bbb011b441c34","department":"Directing","job":"Director"},{"adult":false,"gender":0,"id":2087770,"known_for_department":"Sound","name":"Steffan Andrews","original_name":"Steffan Andrews","popularity":0.2611,"profile_path":null,"credit_id":"653ba2ec519bbb011b441c3d","department":"Sound","job":"Sound"}]}