{"movie_results":[],"person_results":[],"tv_results":[{"adult":false,"backdrop_path":"\/vyC7bYAd3lPHeg47VDz4iZ97wRP.jpg","id":281009,"name":"The Jewel of Section E","original_name":"Ang Mutya ng Section E","overview":"Jay-jay, the only girl in the mischievous Section E, hopes for a fresh start in high school but quickly becomes the target of her rowdy male classmates' pranks and schemes to make her leave. Dubbed their \"Mutya\" (muse), she fights back with wit and charm, turning the tables on her tormentors. Amidst the chaos, unexpected friendships blossom, and hilarious misunderstandings lead to heart-fluttering moments. Can Jay-jay survive the madness of Section E, or will she win over their hearts instead?","poster_path":"\/2wBlN0pC9U1LWmLNTdOuR76NSHe.jpg","media_type":"tv","original_language":"tl","genre_ids":[35,18],"popularity":21.3268,"first_air_date":"2025-01-03","vote_average":8.265,"vote_count":83,"origin_country":["PH"]}],"tv_episode_results":[],"tv_season_results":[]}