{"movie_results":[{"adult":false,"backdrop_path":"\/be5SIsRGMckO8tU9lrLcIik70Dy.jpg","id":1246049,"title":"Dracula","original_title":"Dracula","overview":"In late 15th-century Eastern Europe, Prince Vlad II\u2019s bride is brutally murdered. As a result, he renounces God and damns Heaven itself. Cursed with eternal life, Vlad is reborn as Dracula, an immortal warlord who defies fate in a blood-soaked crusade to wrench his lost love back from death.","poster_path":"\/libhghrUSBSEdHgF9uP1SQES0nQ.jpg","media_type":"movie","original_language":"fr","genre_ids":[27,14,10749],"popularity":35.5618,"release_date":"2025-07-30","video":false,"vote_average":7.122,"vote_count":931}],"person_results":[],"tv_results":[],"tv_episode_results":[],"tv_season_results":[]}