{"movie_results":[{"adult":false,"backdrop_path":"\/waUDWpsm3oCrzU9P4XnsBAh2cso.jpg","id":1266127,"title":"Ready or Not: Here I Come","original_title":"Ready or Not: Here I Come","overview":"Moments after surviving an all-out attack from the Le Domas family, Grace discovers she\u2019s reached the next level of the nightmarish game \u2014 and this time with her estranged sister Faith at her side. Grace has one chance to survive, keep her sister alive, and claim the High Seat of the Council that controls the world. Four rival families are hunting her for the throne, and whoever wins rules it all.","poster_path":"\/13ZcJzSGEqVgDSqsS9U5EkQwPkV.jpg","media_type":"movie","original_language":"en","genre_ids":[27,35],"popularity":56.9025,"release_date":"2026-03-19","video":false,"vote_average":7.432,"vote_count":37}],"person_results":[],"tv_results":[],"tv_episode_results":[],"tv_season_results":[]}